{
  "WEI LAN": { "en": "WEI LAN", "zh-CN": "WEI LAN", "zh-Hant": "WEI LAN" },
  "Lion One": { "en": "Lion One", "zh-CN": "Lion One", "zh-Hant": "Lion One" },
  "AI optical sorting": { "en": "AI optical sorting", "zh-CN": "AI 光学分选", "zh-Hant": "AI 光學分選" },
  "C&D waste": { "en": "C&D waste", "zh-CN": "建筑与拆除废弃物", "zh-Hant": "營建與拆除廢棄物" },
  "feeding": { "en": "feeding", "zh-CN": "给料 / 进料", "zh-Hant": "給料 / 進料" },
  "screening": { "en": "screening", "zh-CN": "筛分", "zh-Hant": "篩分" },
  "recovery": { "en": "recovery", "zh-CN": "回收", "zh-Hant": "回收" },
  "resource recovery center": { "en": "resource recovery center", "zh-CN": "资源回收中心", "zh-Hant": "資源回收中心" },
  "footprint": { "en": "footprint", "zh-CN": "占地面积", "zh-Hant": "佔地面積" },
  "bulky waste": { "en": "bulky waste", "zh-CN": "大件废弃物", "zh-Hant": "大型廢棄物" },
  "air separation": { "en": "air separation", "zh-CN": "气流分离", "zh-Hant": "氣流分離" },
  "baling": { "en": "baling", "zh-CN": "打包", "zh-Hant": "打包" },
  "feed size": { "en": "feed size", "zh-CN": "进料粒径", "zh-Hant": "進料粒徑" },
  "output fraction": { "en": "output fraction", "zh-CN": "产出组分", "zh-Hant": "產出組分" },
  "case actions": { "en": "case actions", "zh-CN": "案例操作", "zh-Hant": "案例操作" },
  "qualifications and honors": { "en": "qualifications and honors", "zh-CN": "资质与荣誉", "zh-Hant": "資質與榮譽" },
  "colored HDPE": { "en": "colored HDPE", "zh-CN": "有色 HDPE", "zh-Hant": "有色 HDPE" },
  "PET": { "en": "PET", "zh-CN": "PET", "zh-Hant": "PET" },
  "HDPE": { "en": "HDPE", "zh-CN": "HDPE", "zh-Hant": "HDPE" },
  "PP": { "en": "PP", "zh-CN": "PP", "zh-Hant": "PP" },
  "PS": { "en": "PS", "zh-CN": "PS", "zh-Hant": "PS" },
  "PE": { "en": "PE", "zh-CN": "PE", "zh-Hant": "PE" },
  "CO2": { "en": "CO2", "zh-CN": "CO2", "zh-Hant": "CO2" },
  "GL01V1-5": { "en": "GL01V1-5", "zh-CN": "GL01V1-5", "zh-Hant": "GL01V1-5" },
  "GL01V2-9": { "en": "GL01V2-9", "zh-CN": "GL01V2-9", "zh-Hant": "GL01V2-9" },
  "GL01V3-10": { "en": "GL01V3-10", "zh-CN": "GL01V3-10", "zh-Hant": "GL01V3-10" },
  "MK-F50": { "en": "MK-F50", "zh-CN": "MK-F50", "zh-Hant": "MK-F50" },
  "SYS-*": { "en": "SYS-*", "zh-CN": "SYS-*", "zh-Hant": "SYS-*" },
  "CAM-*": { "en": "CAM-*", "zh-CN": "CAM-*", "zh-Hant": "CAM-*" },
  "M-*": { "en": "M-*", "zh-CN": "M-*", "zh-Hant": "M-*" },
  "Q-*": { "en": "Q-*", "zh-CN": "Q-*", "zh-Hant": "Q-*" },
  "RFQ-*": { "en": "RFQ-*", "zh-CN": "RFQ-*", "zh-Hant": "RFQ-*" },
  "DATA-*": { "en": "DATA-*", "zh-CN": "DATA-*", "zh-Hant": "DATA-*" },
  "MRF": { "en": "MRF", "zh-CN": "MRF", "zh-Hant": "MRF" },
  "PLC": { "en": "PLC", "zh-CN": "PLC", "zh-Hant": "PLC" },
  "DCS": { "en": "DCS", "zh-CN": "DCS", "zh-Hant": "DCS" },
  "IoT": { "en": "IoT", "zh-CN": "IoT", "zh-Hant": "IoT" },
  "ISO": { "en": "ISO", "zh-CN": "ISO", "zh-Hant": "ISO" },
  "throughput": { "en": "throughput", "zh-CN": "处理量", "zh-Hant": "處理量" },
  "sorting rate": { "en": "sorting rate", "zh-CN": "分选率", "zh-Hant": "分選率" },
  "Request Quote": { "en": "Request Quote", "zh-CN": "获取报价", "zh-Hant": "索取報價" },
  "Service & Support": { "en": "Service & Support", "zh-CN": "服务与支持", "zh-Hant": "服務與支援" }
}
